jupyternetes_clients/__init__.py
jupyternetes_clients/_version.py
jupyternetes_clients/clients/__init__.py
jupyternetes_clients/clients/kubernetes_client.py
jupyternetes_clients/clients/notebook_instance_client.py
jupyternetes_clients-0.1.82.dist-info/METADATA
jupyternetes_clients-0.1.82.dist-info/WHEEL
jupyternetes_clients-0.1.82.dist-info/RECORD
