Metadata-Version: 2.4
Name: jupyternetes_clients
Version: 0.1.82
Dynamic: Requires-Dist
Summary: Kadense Jupyternetes Kubernetes Clients
Project-URL: Homepage, https://github.com/headinthecloudsolutions/kadense
Project-URL: Issues, https://github.com/headinthecloudsolutions/kadense/issues
Author-email: Shaun Turner <shaun.turner@headinthecloudsolutions.co.uk>
Keywords: clients,jupyterhub,jupyternetes,kadense
Classifier: License :: OSI Approved :: MIT License
Classifier: Operating System :: OS Independent
Classifier: Programming Language :: Python :: 3
Requires-Python: >=3.8
